py101/__init__.py
py101/boilerplate/README.es.rst
py101/boilerplate/README.rst
py101/boilerplate/SOLUTION.rst
py101/boilerplate/__init__.py
py101/classes/README.es.rst
py101/classes/README.rst
py101/classes/SOLUTION.rst
py101/classes/__init__.py
py101/conditions/README.es.rst
py101/conditions/README.rst
py101/conditions/SOLUTION.rst
py101/conditions/__init__.py
py101/dictionaries/README.es.rst
py101/dictionaries/README.rst
py101/dictionaries/SOLUTION.rst
py101/dictionaries/__init__.py
py101/formatting/README.es.rst
py101/formatting/README.rst
py101/formatting/SOLUTION.rst
py101/formatting/__init__.py
py101/functions/README.es.rst
py101/functions/README.rst
py101/functions/SOLUTION.rst
py101/functions/__init__.py
py101/introduction/README.es.rst
py101/introduction/README.rst
py101/introduction/SOLUTION.es.rst
py101/introduction/SOLUTION.rst
py101/introduction/__init__.py
py101/lists/README.es.rst
py101/lists/README.rst
py101/lists/SOLUTION.rst
py101/lists/__init__.py
py101/locale/en/LC_MESSAGES/pyschool.mo
py101/locale/en/LC_MESSAGES/pyschool.po
py101/locale/es/LC_MESSAGES/pyschool.mo
py101/locale/es/LC_MESSAGES/pyschool.po
py101/loops/README.es.rst
py101/loops/README.rst
py101/loops/SOLUTION.rst
py101/loops/__init__.py
py101/modules/README.es.rst
py101/modules/README.rst
py101/modules/SOLUTION.rst
py101/modules/__init__.py
py101/operators/README.es.rst
py101/operators/README.rst
py101/operators/SOLUTION.rst
py101/operators/__init__.py
py101/strings/README.es.rst
py101/strings/README.rst
py101/strings/SOLUTION.rst
py101/strings/__init__.py
py101/variables/README.es.rst
py101/variables/README.rst
py101/variables/SOLUTION.es.rst
py101/variables/SOLUTION.rst
py101/variables/__init__.py
py101-0.0.2.dist-info/DESCRIPTION.rst
py101-0.0.2.dist-info/METADATA
py101-0.0.2.dist-info/RECORD
py101-0.0.2.dist-info/WHEEL
py101-0.0.2.dist-info/entry_points.txt
py101-0.0.2.dist-info/metadata.json
py101-0.0.2.dist-info/top_level.txt
