Metadata-Version: 2.0
Name: py101
Version: 0.0.2
Summary: Learn Python Basics from the command line.
Home-page: https://github.com/sophilabs/py101
Author: Sophilabs
Author-email: hi@sophilabs.co
License: MIT license
Keywords: py101
Platform: UNKNOWN
Classifier: Development Status :: 2 - Pre-Alpha
Classifier: Intended Audience :: Developers
Classifier: License :: OSI Approved :: MIT License
Classifier: Natural Language :: English
Classifier: Programming Language :: Python :: 3
Classifier: Programming Language :: Python :: 3.3
Classifier: Programming Language :: Python :: 3.4
Classifier: Programming Language :: Python :: 3.5
Requires-Python: !=2, !=3.0.*, !=3.1.*, !=3.2.*, <4
Requires-Dist: story (>=1.2.3)
